LICENSE
README.md
setup.py
np_vmd/__init__.py
np_vmd/misc.py
np_vmd/sdof_funcs.py
np_vmd/tdof_MCK.py
np_vmd/tdof_system.py
np_vmd/sho_class/SHO_sdof_class.py
np_vmd/sho_class/__init__.py
np_vmd/sho_class/example_comparison_free.py
np_vmd/sho_class/example_sho.py
np_vmd/sho_class/sdof_sympy.py
nphmu_vdm.egg-info/PKG-INFO
nphmu_vdm.egg-info/SOURCES.txt
nphmu_vdm.egg-info/dependency_links.txt
nphmu_vdm.egg-info/requires.txt
nphmu_vdm.egg-info/top_level.txt
tests/test_sdof_funcs.py
tests/test_sdof_system.py
tests/test_sdof_system_response.py
tests/test_tdof_MCK.py
tests/test_tdof_MCK_damping.py
tests/test_tdof_MCK_forced.py
tests/test_tdof_system.py