Metadata-Version: 2.1
Name: nphmu-vdm
Version: 0.0.2
Summary: A package for Vibrations and Machine Dynamics
Home-page: 
Author: N. Papadakis
Author-email: npapnet@gmail.com
Classifier: Programming Language :: Python :: 3
Classifier: License :: OSI Approved :: MIT License
Classifier: Operating System :: OS Independent
Requires-Python: >=3.6
License-File: LICENSE
